screen.py
dosbox_screen-1.1.5.dist-info/LICENSE
dosbox_screen-1.1.5.dist-info/METADATA
dosbox_screen-1.1.5.dist-info/WHEEL
dosbox_screen-1.1.5.dist-info/top_level.txt
dosbox_screen-1.1.5.dist-info/RECORD
