Metadata-Version: 2.1
Name: dosbox-screen
Version: 1.1.5
Summary: The Screen class lets you to do positioned writes to the dos terminal.
Home-page: https://github.com/thebjorn/doscmd-screen
Author: Bjorn Pettersen
Author-email: bjorn@tkbe.org
License: BSD
Download-URL: https://github.com/thebjorn/doscmd-screen
Platform: UNKNOWN
Classifier: Development Status :: 5 - Production/Stable
Classifier: Environment :: Win32 (MS Windows)
Classifier: Intended Audience :: Developers
Classifier: License :: OSI Approved :: BSD License
Classifier: Operating System :: Microsoft :: MS-DOS
Classifier: Operating System :: POSIX :: Linux
Classifier: Programming Language :: Python
Classifier: Topic :: Software Development :: Libraries
Classifier: Topic :: System :: Shells
Classifier: Topic :: Terminals
Requires: colorama
Requires-Dist: colorama
